provider_hub/__init__.py
provider_hub/cli.py
provider_hub/exceptions.py
provider_hub/test_connection.py
provider_hub/core/__init__.py
provider_hub/core/base.py
provider_hub/core/config.py
provider_hub/core/llm.py
provider_hub/providers/__init__.py
provider_hub/providers/deepseek.py
provider_hub/providers/doubao.py
provider_hub/providers/gemini.py
provider_hub/providers/openai.py
provider_hub/providers/openai_compatible.py
provider_hub/providers/qwen.py
provider_hub/utils/__init__.py
provider_hub/utils/env.py
provider_hub/utils/image.py
provider_hub-0.7.0.dist-info/licenses/LICENSE
provider_hub-0.7.0.dist-info/METADATA
provider_hub-0.7.0.dist-info/WHEEL
provider_hub-0.7.0.dist-info/entry_points.txt
provider_hub-0.7.0.dist-info/top_level.txt
provider_hub-0.7.0.dist-info/RECORD
