Metadata-Version: 2.4
Name: provider_hub
Version: 0.7.0
Summary: Unified interface for accessing multiple LLM providers
Author: Djanghao
License-Expression: MIT
Project-URL: Homepage, https://github.com/Djanghao/provider_hub
Project-URL: Repository, https://github.com/Djanghao/provider_hub.git
Project-URL: Issues, https://github.com/Djanghao/provider_hub/issues
Classifier: Development Status :: 3 - Alpha
Classifier: Intended Audience :: Developers
Classifier: Programming Language :: Python :: 3
Classifier: Programming Language :: Python :: 3.7
Classifier: Programming Language :: Python :: 3.8
Classifier: Programming Language :: Python :: 3.9
Classifier: Programming Language :: Python :: 3.10
Classifier: Programming Language :: Python :: 3.11
Requires-Python: >=3.7
License-File: LICENSE
Requires-Dist: openai>=1.0.0
Requires-Dist: volcengine-python-sdk[ark]>=1.0.0
Requires-Dist: python-dotenv>=0.19.0
Requires-Dist: tenacity>=8.0.0
Requires-Dist: google-genai>=0.3.0
Dynamic: license-file
Dynamic: requires-python
